pyramid_debugtoolbar_security
