Metadata-Version: 1.1
Name: pyramid-debugtoolbar-security
Version: 0.1.2
Summary: security panel for pyramid_debugtoolbar (principals, context acl, view permission)
Home-page: https://bitbucket.org/shimizukawa/pyramid_debugtoolbar_security
Author: shimizukawa
Author-email: shimizukawa@gmail.com
License: Apache Software License
Platform: UNKNOWN
Classifier: Development Status :: 3 - Alpha
Classifier: Programming Language :: Python
Classifier: Framework :: Pyramid
Classifier: Topic :: Software Development :: Libraries :: Python Modules
Classifier: Programming Language :: Python
Classifier: Programming Language :: Python :: 2.7
